{
  "$schema": "https://json.schemastore.org/tsconfig",
  "compilerOptions": {
    "allowJs": false,
    "declaration": false,
    "erasableSyntaxOnly": true,
    "exactOptionalPropertyTypes": true,
    "experimentalDecorators": true,
    "forceConsistentCasingInFileNames": true,
    "importHelpers": true,
    "incremental": false,
    "isolatedDeclarations": false,
    "isolatedModules": true,
    "jsx": "preserve",
    "lib": ["dom", "esnext"],
    "module": "esnext",
    "moduleResolution": "bundler",
    "newLine": "lf",
    "noEmit": true,
    "noImplicitAny": true,
    "noUncheckedIndexedAccess": true,
    "noUncheckedSideEffectImports": false,
    "noUnusedLocals": true,
    "noUnusedParameters": true,
    "resolveJsonModule": true,
    "skipLibCheck": true,
    "strict": true,
    "verbatimModuleSyntax": true
  },
  "vueCompilerOptions": {
    "strictCssModules": true,
    "strictTemplates": true
  }
}
